[{"TradeDirection":1,"TradeOutcome":1,"PreTradeBars":[{"DataBar":{"BarTypeTraits":1,"OpenTraits":-0.10606060606060606,"CloseTraits":0.95454545454545459,"Atr":22.75},"DeltaBar":{"BarTypeTraits":1,"OpenTraits":-0.38801261829652994,"CloseTraits":0.91167192429022081,"Atr":22.75},"OrderFlowData":{"DeltaPercentage":11.789999999999999,"ImbalanceMetric":0.99999999998}},{"DataBar":{"BarTypeTraits":-1,"OpenTraits":-0.5714285714285714,"CloseTraits":-0.8571428571428571,"Atr":21.850000000000001},"DeltaBar":{"BarTypeTraits":-1,"OpenTraits":-0.50704225352112675,"CloseTraits":-0.87323943661971826,"Atr":21.850000000000001},"OrderFlowData":{"DeltaPercentage":-1.1200000000000001,"ImbalanceMetric":1.99999999995}},{"DataBar":{"BarTypeTraits":1,"OpenTraits":-0.68831168831168832,"CloseTraits":0.94805194805194803,"Atr":21.710000000000001},"DeltaBar":{"BarTypeTraits":1,"OpenTraits":-0.84810126582278478,"CloseTraits":0.98734177215189878,"Atr":21.710000000000001},"OrderFlowData":{"DeltaPercentage":13.74,"ImbalanceMetric":4.9999999999}}],"CurrentBar":{"DataBar":{"BarTypeTraits":1,"OpenTraits":-0.58139534883720934,"CloseTraits":1,"Atr":20.09},"DeltaBar":{"BarTypeTraits":1,"OpenTraits":-0.58282208588957052,"CloseTraits":0.81595092024539873,"Atr":20.09},"OrderFlowData":{"DeltaPercentage":4.4000000000000004,"ImbalanceMetric":0.99999999989999999}}},{"TradeDirection":0,"TradeOutcome":1,"PreTradeBars":[{"DataBar":{"BarTypeTraits":-1,"OpenTraits":-0.40476190476190477,"CloseTraits":-0.54761904761904767,"Atr":21.149999999999999},"DeltaBar":{"BarTypeTraits":-1,"OpenTraits":-0.57894736842105265,"CloseTraits":-0.27368421052631581,"Atr":21.149999999999999},"OrderFlowData":{"DeltaPercentage":1.8200000000000001,"ImbalanceMetric":0}},{"DataBar":{"BarTypeTraits":1,"OpenTraits":-0.8545454545454545,"CloseTraits":0.52727272727272723,"Atr":21.300000000000001},"DeltaBar":{"BarTypeTraits":1,"OpenTraits":-0.88191881918819193,"CloseTraits":-0.055350553505535055,"Atr":21.300000000000001},"OrderFlowData":{"DeltaPercentage":5.2800000000000002,"ImbalanceMetric":1.99999999998}},{"DataBar":{"BarTypeTraits":-1,"OpenTraits":0.7407407407407407,"CloseTraits":-0.72222222222222221,"Atr":21.82},"DeltaBar":{"BarTypeTraits":-1,"OpenTraits":0.7931034482758621,"CloseTraits":-0.22758620689655173,"Atr":21.82},"OrderFlowData":{"DeltaPercentage":-6.71,"ImbalanceMetric":1.99999999995}}],"CurrentBar":{"DataBar":{"BarTypeTraits":-1,"OpenTraits":0.35483870967741937,"CloseTraits":-1,"Atr":20.059999999999999},"DeltaBar":{"BarTypeTraits":-1,"OpenTraits":0.39583333333333331,"CloseTraits":-0.97916666666666663,"Atr":20.059999999999999},"OrderFlowData":{"DeltaPercentage":-17,"ImbalanceMetric":-2.9999999999}}},{"TradeDirection":1,"TradeOutcome":0,"PreTradeBars":[{"DataBar":{"BarTypeTraits":-1,"OpenTraits":-0.079365079365079361,"CloseTraits":-0.52380952380952384,"Atr":21.489999999999998},"DeltaBar":{"BarTypeTraits":-1,"OpenTraits":-0.16339869281045752,"CloseTraits":-0.35294117647058826,"Atr":21.489999999999998},"OrderFlowData":{"DeltaPercentage":-0.85999999999999999,"ImbalanceMetric":2.9999999999}},{"DataBar":{"BarTypeTraits":-1,"OpenTraits":-0.12820512820512819,"CloseTraits":-0.69230769230769229,"Atr":21.27},"DeltaBar":{"BarTypeTraits":-1,"OpenTraits":0.44910179640718562,"CloseTraits":-0.58083832335329344,"Atr":21.27},"OrderFlowData":{"DeltaPercentage":-4.5300000000000002,"ImbalanceMetric":-1.99999999995}},{"DataBar":{"BarTypeTraits":1,"OpenTraits":-0.47058823529411764,"CloseTraits":-0.23529411764705882,"Atr":20.52},"DeltaBar":{"BarTypeTraits":1,"OpenTraits":-0.44827586206896552,"CloseTraits":0.17241379310344829,"Atr":20.52},"OrderFlowData":{"DeltaPercentage":1.6699999999999999,"ImbalanceMetric":0}}],"CurrentBar":{"DataBar":{"BarTypeTraits":1,"OpenTraits":-0.93617021276595747,"CloseTraits":1,"Atr":19.670000000000002},"DeltaBar":{"BarTypeTraits":1,"OpenTraits":-1,"CloseTraits":1,"Atr":19.670000000000002},"OrderFlowData":{"DeltaPercentage":20.390000000000001,"ImbalanceMetric":1.9999999999666667}}},{"TradeDirection":0,"TradeOutcome":0,"PreTradeBars":[{"DataBar":{"BarTypeTraits":1,"OpenTraits":-0.91176470588235292,"CloseTraits":0.94117647058823528,"Atr":21.129999999999999},"DeltaBar":{"BarTypeTraits":1,"OpenTraits":-0.80152671755725191,"CloseTraits":0.87786259541984735,"Atr":21.129999999999999},"OrderFlowData":{"DeltaPercentage":8.9299999999999997,"ImbalanceMetric":0}},{"DataBar":{"BarTypeTraits":-1,"OpenTraits":-0.30555555555555558,"CloseTraits":-0.47222222222222221,"Atr":20.84},"DeltaBar":{"BarTypeTraits":-1,"OpenTraits":-0.54285714285714282,"CloseTraits":-0.69999999999999996,"Atr":20.84},"OrderFlowData":{"DeltaPercentage":-0.98999999999999999,"ImbalanceMetric":0}},{"DataBar":{"BarTypeTraits":-1,"OpenTraits":0.41353383458646614,"CloseTraits":-0.63909774436090228,"Atr":21.530000000000001},"DeltaBar":{"BarTypeTraits":-1,"OpenTraits":0.59545454545454546,"CloseTraits":-0.76818181818181819,"Atr":21.530000000000001},"OrderFlowData":{"DeltaPercentage":-16.109999999999999,"ImbalanceMetric":-3.9999999999}}],"CurrentBar":{"DataBar":{"BarTypeTraits":-1,"OpenTraits":0.80246913580246915,"CloseTraits":-1,"Atr":22.780000000000001},"DeltaBar":{"BarTypeTraits":-1,"OpenTraits":0.94059405940594054,"CloseTraits":-0.94059405940594054,"Atr":22.780000000000001},"OrderFlowData":{"DeltaPercentage":-6.3200000000000003,"ImbalanceMetric":-3.9999999999}}},{"TradeDirection":0,"TradeOutcome":1,"PreTradeBars":[{"DataBar":{"BarTypeTraits":-1,"OpenTraits":0.5,"CloseTraits":-0.54166666666666663,"Atr":23.870000000000001},"DeltaBar":{"BarTypeTraits":-1,"OpenTraits":0.95652173913043481,"CloseTraits":-0.82608695652173914,"Atr":23.870000000000001},"OrderFlowData":{"DeltaPercentage":-17.949999999999999,"ImbalanceMetric":-1.9999999999}},{"DataBar":{"BarTypeTraits":-1,"OpenTraits":-0.56521739130434778,"CloseTraits":-0.59420289855072461,"Atr":23.140000000000001},"DeltaBar":{"BarTypeTraits":-1,"OpenTraits":-0.77931034482758621,"CloseTraits":-0.4206896551724138,"Atr":23.140000000000001},"OrderFlowData":{"DeltaPercentage":2.3500000000000001,"ImbalanceMetric":0}},{"DataBar":{"BarTypeTraits":-1,"OpenTraits":0.78723404255319152,"CloseTraits":-0.74468085106382975,"Atr":23.960000000000001},"DeltaBar":{"BarTypeTraits":-1,"OpenTraits":0.93364928909952605,"CloseTraits":-0.74881516587677721,"Atr":23.960000000000001},"OrderFlowData":{"DeltaPercentage":-15.34,"ImbalanceMetric":-1.9999999999666667}}],"CurrentBar":{"DataBar":{"BarTypeTraits":-1,"OpenTraits":-0.27272727272727271,"CloseTraits":-1,"Atr":24.149999999999999},"DeltaBar":{"BarTypeTraits":-1,"OpenTraits":-0.041095890410958902,"CloseTraits":-0.95890410958904104,"Atr":24.149999999999999},"OrderFlowData":{"DeltaPercentage":-4.54,"ImbalanceMetric":-2.9999999999}}},{"TradeDirection":1,"TradeOutcome":0,"PreTradeBars":[{"DataBar":{"BarTypeTraits":1,"OpenTraits":-0.89010989010989006,"CloseTraits":-0.032967032967032968,"Atr":21.629999999999999},"DeltaBar":{"BarTypeTraits":1,"OpenTraits":-0.92131147540983604,"CloseTraits":0.75081967213114753,"Atr":21.629999999999999},"OrderFlowData":{"DeltaPercentage":16.710000000000001,"ImbalanceMetric":4.9999999999285718}},{"DataBar":{"BarTypeTraits":1,"OpenTraits":-0.91044776119402981,"CloseTraits":-0.16417910447761194,"Atr":20.949999999999999},"DeltaBar":{"BarTypeTraits":1,"OpenTraits":-0.54609929078014185,"CloseTraits":0.48936170212765956,"Atr":20.949999999999999},"OrderFlowData":{"DeltaPercentage":5.8700000000000001,"ImbalanceMetric":1.9999999999}},{"DataBar":{"BarTypeTraits":1,"OpenTraits":-0.78787878787878785,"CloseTraits":0.63636363636363635,"Atr":19.329999999999998},"DeltaBar":{"BarTypeTraits":1,"OpenTraits":-0.88944723618090449,"CloseTraits":0.97989949748743721,"Atr":19.329999999999998},"OrderFlowData":{"DeltaPercentage":14.91,"ImbalanceMetric":1.9999999999}}],"CurrentBar":{"DataBar":{"BarTypeTraits":1,"OpenTraits":-0.76811594202898548,"CloseTraits":1,"Atr":21.050000000000001},"DeltaBar":{"BarTypeTraits":1,"OpenTraits":-0.8515625,"CloseTraits":0.9921875,"Atr":21.050000000000001},"OrderFlowData":{"DeltaPercentage":16.100000000000001,"ImbalanceMetric":2.9999999999}}},{"TradeDirection":1,"TradeOutcome":0,"PreTradeBars":[{"DataBar":{"BarTypeTraits":1,"OpenTraits":-0.8202247191011236,"CloseTraits":0.48314606741573035,"Atr":20.190000000000001},"DeltaBar":{"BarTypeTraits":1,"OpenTraits":-0.9956521739130435,"CloseTraits":0.73478260869565215,"Atr":20.190000000000001},"OrderFlowData":{"DeltaPercentage":19.120000000000001,"ImbalanceMetric":-0.99999999998888889}},{"DataBar":{"BarTypeTraits":1,"OpenTraits":-0.47619047619047616,"CloseTraits":0.19047619047619047,"Atr":18.789999999999999},"DeltaBar":{"BarTypeTraits":1,"OpenTraits":-0.27007299270072993,"CloseTraits":-0.98540145985401462,"Atr":18.789999999999999},"OrderFlowData":{"DeltaPercentage":-3.6000000000000001,"ImbalanceMetric":-0.99999999998}},{"DataBar":{"BarTypeTraits":1,"OpenTraits":-0.14999999999999999,"CloseTraits":0.77500000000000002,"Atr":19.010000000000002},"DeltaBar":{"BarTypeTraits":1,"OpenTraits":0.26582278481012656,"CloseTraits":-0.310126582278481,"Atr":19.010000000000002},"OrderFlowData":{"DeltaPercentage":-3.7200000000000002,"ImbalanceMetric":-0.99999999996666666}}],"CurrentBar":{"DataBar":{"BarTypeTraits":1,"OpenTraits":-0.93333333333333335,"CloseTraits":1,"Atr":19.510000000000002},"DeltaBar":{"BarTypeTraits":1,"OpenTraits":-0.76744186046511631,"CloseTraits":0.96899224806201545,"Atr":19.510000000000002},"OrderFlowData":{"DeltaPercentage":8.4800000000000004,"ImbalanceMetric":2.9999999999}}},{"TradeDirection":1,"TradeOutcome":0,"PreTradeBars":[{"DataBar":{"BarTypeTraits":1,"OpenTraits":-0.91208791208791207,"CloseTraits":0.93406593406593408,"Atr":20.920000000000002},"DeltaBar":{"BarTypeTraits":1,"OpenTraits":-0.95714285714285718,"CloseTraits":0.91428571428571426,"Atr":20.920000000000002},"OrderFlowData":{"DeltaPercentage":18.399999999999999,"ImbalanceMetric":4.9999999999285718}},{"DataBar":{"BarTypeTraits":-1,"OpenTraits":0.19047619047619047,"CloseTraits":-0.61904761904761907,"Atr":19.829999999999998},"DeltaBar":{"BarTypeTraits":-1,"OpenTraits":0.94964028776978415,"CloseTraits":-0.97841726618705038,"Atr":19.829999999999998},"OrderFlowData":{"DeltaPercentage":-14.73,"ImbalanceMetric":0}},{"DataBar":{"BarTypeTraits":1,"OpenTraits":-0.1111111111111111,"CloseTraits":0.48148148148148145,"Atr":20.440000000000001},"DeltaBar":{"BarTypeTraits":1,"OpenTraits":0.75845410628019327,"CloseTraits":-0.97101449275362317,"Atr":20.440000000000001},"OrderFlowData":{"DeltaPercentage":-12.08,"ImbalanceMetric":-0.99999999998}}],"CurrentBar":{"DataBar":{"BarTypeTraits":1,"OpenTraits":0,"CloseTraits":1,"Atr":19.809999999999999},"DeltaBar":{"BarTypeTraits":1,"OpenTraits":-0.28155339805825241,"CloseTraits":0.91262135922330101,"Atr":19.809999999999999},"OrderFlowData":{"DeltaPercentage":14.66,"ImbalanceMetric":3.9999999999}}},{"TradeDirection":1,"TradeOutcome":1,"PreTradeBars":[{"DataBar":{"BarTypeTraits":1,"OpenTraits":0.037037037037037035,"CloseTraits":0.40740740740740738,"Atr":17.949999999999999},"DeltaBar":{"BarTypeTraits":1,"OpenTraits":1,"CloseTraits":-0.52631578947368418,"Atr":17.949999999999999},"OrderFlowData":{"DeltaPercentage":-10.199999999999999,"ImbalanceMetric":-0.99999999989999999}},{"DataBar":{"BarTypeTraits":1,"OpenTraits":-0.89743589743589747,"CloseTraits":0.48717948717948717,"Atr":16.75},"DeltaBar":{"BarTypeTraits":1,"OpenTraits":-0.85987261146496818,"CloseTraits":0.68152866242038213,"Atr":16.75},"OrderFlowData":{"DeltaPercentage":21.899999999999999,"ImbalanceMetric":-0.99999999989999999}},{"DataBar":{"BarTypeTraits":1,"OpenTraits":-0.46666666666666667,"CloseTraits":-0.26666666666666666,"Atr":17.309999999999999},"DeltaBar":{"BarTypeTraits":1,"OpenTraits":-0.70454545454545459,"CloseTraits":-0.25,"Atr":17.309999999999999},"OrderFlowData":{"DeltaPercentage":3.5099999999999998,"ImbalanceMetric":0}}],"CurrentBar":{"DataBar":{"BarTypeTraits":1,"OpenTraits":-0.9555555555555556,"CloseTraits":0.8666666666666667,"Atr":17.949999999999999},"DeltaBar":{"BarTypeTraits":1,"OpenTraits":-0.93000000000000005,"CloseTraits":0.93000000000000005,"Atr":17.949999999999999},"OrderFlowData":{"DeltaPercentage":17.98,"ImbalanceMetric":1.9999999999}}},{"TradeDirection":0,"TradeOutcome":1,"PreTradeBars":[{"DataBar":{"BarTypeTraits":1,"OpenTraits":-0.75510204081632648,"CloseTraits":0.7142857142857143,"Atr":16.460000000000001},"DeltaBar":{"BarTypeTraits":1,"OpenTraits":-0.92653061224489797,"CloseTraits":0.94285714285714284,"Atr":16.460000000000001},"OrderFlowData":{"DeltaPercentage":26.199999999999999,"ImbalanceMetric":2.9999999999}},{"DataBar":{"BarTypeTraits":-1,"OpenTraits":0.17241379310344829,"CloseTraits":-0.17241379310344829,"Atr":15.35},"DeltaBar":{"BarTypeTraits":-1,"OpenTraits":0.39393939393939392,"CloseTraits":-0.19191919191919191,"Atr":15.35},"OrderFlowData":{"DeltaPercentage":-3.2200000000000002,"ImbalanceMetric":0.99999999996666666}},{"DataBar":{"BarTypeTraits":-1,"OpenTraits":-0.18181818181818182,"CloseTraits":-0.36363636363636365,"Atr":15.460000000000001},"DeltaBar":{"BarTypeTraits":-1,"OpenTraits":-0.90697674418604646,"CloseTraits":-0.30232558139534882,"Atr":15.460000000000001},"OrderFlowData":{"DeltaPercentage":2.7000000000000002,"ImbalanceMetric":0}}],"CurrentBar":{"DataBar":{"BarTypeTraits":-1,"OpenTraits":0.90000000000000002,"CloseTraits":-0.90000000000000002,"Atr":15.68},"DeltaBar":{"BarTypeTraits":-1,"OpenTraits":0.58620689655172409,"CloseTraits":-1,"Atr":15.68},"OrderFlowData":{"DeltaPercentage":-16.02,"ImbalanceMetric":-2.9999999999}}},{"TradeDirection":0,"TradeOutcome":1,"PreTradeBars":[{"DataBar":{"BarTypeTraits":-1,"OpenTraits":1,"CloseTraits":-0.33333333333333331,"Atr":15.68},"DeltaBar":{"BarTypeTraits":-1,"OpenTraits":1,"CloseTraits":-0.77358490566037741,"Atr":15.68},"OrderFlowData":{"DeltaPercentage":-18.050000000000001,"ImbalanceMetric":-0.99999999989999999}},{"DataBar":{"BarTypeTraits":-1,"OpenTraits":0.93939393939393945,"CloseTraits":-0.33333333333333331,"Atr":16.239999999999998},"DeltaBar":{"BarTypeTraits":-1,"OpenTraits":0.98425196850393704,"CloseTraits":-0.57480314960629919,"Atr":16.239999999999998},"OrderFlowData":{"DeltaPercentage":-13.449999999999999,"ImbalanceMetric":-1.9999999999}},{"DataBar":{"BarTypeTraits":-1,"OpenTraits":0.58620689655172409,"CloseTraits":-0.58620689655172409,"Atr":15.24},"DeltaBar":{"BarTypeTraits":-1,"OpenTraits":0.32000000000000001,"CloseTraits":-0.62,"Atr":15.24},"OrderFlowData":{"DeltaPercentage":-7.8700000000000001,"ImbalanceMetric":0}}],"CurrentBar":{"DataBar":{"BarTypeTraits":-1,"OpenTraits":0.76923076923076927,"CloseTraits":-1,"Atr":15.630000000000001},"DeltaBar":{"BarTypeTraits":-1,"OpenTraits":0.68627450980392157,"CloseTraits":-0.96078431372549022,"Atr":15.630000000000001},"OrderFlowData":{"DeltaPercentage":-13.300000000000001,"ImbalanceMetric":-2.9999999999}}}]