[{"TradeDirection":0,"TradeOutcome":1,"PreTradeBars":[{"DataBar":{"BarTypeTraits":1,"OpenTraits":-0.73493975903614461,"CloseTraits":-0.03614457831325301,"Atr":17.34},"DeltaBar":{"BarTypeTraits":1,"OpenTraits":-0.50264550264550267,"CloseTraits":0.72486772486772488,"Atr":17.34},"OrderFlowData":{"DeltaPercentage":4.96,"ImbalanceMetric":2.9999999999571427}},{"DataBar":{"BarTypeTraits":-1,"OpenTraits":0.84210526315789469,"CloseTraits":-1,"Atr":17.48},"DeltaBar":{"BarTypeTraits":-1,"OpenTraits":0.98202247191011238,"CloseTraits":-0.93707865168539328,"Atr":17.48},"OrderFlowData":{"DeltaPercentage":-14.76,"ImbalanceMetric":-1.99999999995}},{"DataBar":{"BarTypeTraits":-1,"OpenTraits":-0.12643678160919541,"CloseTraits":-0.7931034482758621,"Atr":18.75},"DeltaBar":{"BarTypeTraits":-1,"OpenTraits":0.88,"CloseTraits":-0.26400000000000001,"Atr":18.75},"OrderFlowData":{"DeltaPercentage":-4.7800000000000002,"ImbalanceMetric":-4.9999999999285718}}],"CurrentBar":{"DataBar":{"BarTypeTraits":-1,"OpenTraits":0.59999999999999998,"CloseTraits":-0.90000000000000002,"Atr":17.890000000000001},"DeltaBar":{"BarTypeTraits":-1,"OpenTraits":1,"CloseTraits":-0.98870056497175141,"Atr":17.890000000000001},"OrderFlowData":{"DeltaPercentage":-12.67,"ImbalanceMetric":-4.9999999999}}},{"TradeDirection":0,"TradeOutcome":0,"PreTradeBars":[{"DataBar":{"BarTypeTraits":-1,"OpenTraits":0.7142857142857143,"CloseTraits":-0.36507936507936506,"Atr":16.100000000000001},"DeltaBar":{"BarTypeTraits":-1,"OpenTraits":0.93596059113300489,"CloseTraits":-0.7931034482758621,"Atr":16.100000000000001},"OrderFlowData":{"DeltaPercentage":-15.470000000000001,"ImbalanceMetric":-1.99999999995}},{"DataBar":{"BarTypeTraits":1,"OpenTraits":-0.53061224489795922,"CloseTraits":0.61224489795918369,"Atr":17.030000000000001},"DeltaBar":{"BarTypeTraits":1,"OpenTraits":-0.85263157894736841,"CloseTraits":0.88070175438596487,"Atr":17.030000000000001},"OrderFlowData":{"DeltaPercentage":18.170000000000002,"ImbalanceMetric":4.9999999999285718}},{"DataBar":{"BarTypeTraits":-1,"OpenTraits":-0.21428571428571427,"CloseTraits":-0.25,"Atr":16.93},"DeltaBar":{"BarTypeTraits":-1,"OpenTraits":-0.73972602739726023,"CloseTraits":0.30136986301369861,"Atr":16.93},"OrderFlowData":{"DeltaPercentage":5.9699999999999998,"ImbalanceMetric":0.99999999998}}],"CurrentBar":{"DataBar":{"BarTypeTraits":-1,"OpenTraits":0.69999999999999996,"CloseTraits":-1,"Atr":17.100000000000001},"DeltaBar":{"BarTypeTraits":-1,"OpenTraits":0.79220779220779225,"CloseTraits":-1,"Atr":17.100000000000001},"OrderFlowData":{"DeltaPercentage":-7.9100000000000001,"ImbalanceMetric":-2.9999999999}}},{"TradeDirection":0,"TradeOutcome":0,"PreTradeBars":[{"DataBar":{"BarTypeTraits":-1,"OpenTraits":0.44186046511627908,"CloseTraits":-0.62790697674418605,"Atr":17.960000000000001},"DeltaBar":{"BarTypeTraits":-1,"OpenTraits":0.80821917808219179,"CloseTraits":-0.79452054794520544,"Atr":17.960000000000001},"OrderFlowData":{"DeltaPercentage":-6.4500000000000002,"ImbalanceMetric":-0.99999999998}},{"DataBar":{"BarTypeTraits":0,"OpenTraits":0.027777777777777776,"CloseTraits":0.027777777777777776,"Atr":17.510000000000002},"DeltaBar":{"BarTypeTraits":0,"OpenTraits":0.52785145888594165,"CloseTraits":-0.2572944297082228,"Atr":17.510000000000002},"OrderFlowData":{"DeltaPercentage":-8.2599999999999998,"ImbalanceMetric":0}},{"DataBar":{"BarTypeTraits":-1,"OpenTraits":0.5757575757575758,"CloseTraits":0.18181818181818182,"Atr":18.809999999999999},"DeltaBar":{"BarTypeTraits":-1,"OpenTraits":-0.64166666666666672,"CloseTraits":0.16666666666666666,"Atr":18.809999999999999},"OrderFlowData":{"DeltaPercentage":4.3600000000000003,"ImbalanceMetric":-1.9999999999666667}}],"CurrentBar":{"DataBar":{"BarTypeTraits":-1,"OpenTraits":0.61538461538461542,"CloseTraits":-0.88461538461538458,"Atr":18.050000000000001},"DeltaBar":{"BarTypeTraits":-1,"OpenTraits":0.49230769230769234,"CloseTraits":-0.72307692307692306,"Atr":18.050000000000001},"OrderFlowData":{"DeltaPercentage":-10.74,"ImbalanceMetric":-0.99999999998}}},{"TradeDirection":0,"TradeOutcome":1,"PreTradeBars":[{"DataBar":{"BarTypeTraits":-1,"OpenTraits":0.875,"CloseTraits":-0.80000000000000004,"Atr":18.260000000000002},"DeltaBar":{"BarTypeTraits":-1,"OpenTraits":0.93193717277486909,"CloseTraits":-0.75392670157068065,"Atr":18.260000000000002},"OrderFlowData":{"DeltaPercentage":-15.470000000000001,"ImbalanceMetric":-1.99999999995}},{"DataBar":{"BarTypeTraits":1,"OpenTraits":-0.2413793103448276,"CloseTraits":0.27586206896551724,"Atr":18.079999999999998},"DeltaBar":{"BarTypeTraits":1,"OpenTraits":-0.84115523465703967,"CloseTraits":0.80505415162454874,"Atr":18.079999999999998},"OrderFlowData":{"DeltaPercentage":13.210000000000001,"ImbalanceMetric":1.9999999999}},{"DataBar":{"BarTypeTraits":-1,"OpenTraits":0.5,"CloseTraits":-0.71052631578947367,"Atr":17.07},"DeltaBar":{"BarTypeTraits":-1,"OpenTraits":0.67472527472527477,"CloseTraits":-0.77582417582417584,"Atr":17.07},"OrderFlowData":{"DeltaPercentage":-16.219999999999999,"ImbalanceMetric":-3.9999999999333333}}],"CurrentBar":{"DataBar":{"BarTypeTraits":-1,"OpenTraits":0.59999999999999998,"CloseTraits":-1,"Atr":17.82},"DeltaBar":{"BarTypeTraits":-1,"OpenTraits":0.82534246575342463,"CloseTraits":-0.99657534246575341,"Atr":17.82},"OrderFlowData":{"DeltaPercentage":-20.620000000000001,"ImbalanceMetric":-2.99999999994}}},{"TradeDirection":0,"TradeOutcome":0,"PreTradeBars":[{"DataBar":{"BarTypeTraits":-1,"OpenTraits":0.64556962025316456,"CloseTraits":-0.16455696202531644,"Atr":16.489999999999998},"DeltaBar":{"BarTypeTraits":-1,"OpenTraits":0.27075812274368233,"CloseTraits":0.73285198555956677,"Atr":16.489999999999998},"OrderFlowData":{"DeltaPercentage":1.76,"ImbalanceMetric":0}},{"DataBar":{"BarTypeTraits":1,"OpenTraits":-0.96875,"CloseTraits":-0.15625,"Atr":16.489999999999998},"DeltaBar":{"BarTypeTraits":1,"OpenTraits":-1,"CloseTraits":0.45945945945945948,"Atr":16.489999999999998},"OrderFlowData":{"DeltaPercentage":12.93,"ImbalanceMetric":0.99999999996666666}},{"DataBar":{"BarTypeTraits":-1,"OpenTraits":-0.020408163265306121,"CloseTraits":-1,"Atr":16.02},"DeltaBar":{"BarTypeTraits":-1,"OpenTraits":-0.39622641509433965,"CloseTraits":-0.94339622641509435,"Atr":16.02},"OrderFlowData":{"DeltaPercentage":-2.5800000000000001,"ImbalanceMetric":0}}],"CurrentBar":{"DataBar":{"BarTypeTraits":-1,"OpenTraits":0.82857142857142863,"CloseTraits":-0.82857142857142863,"Atr":16.010000000000002},"DeltaBar":{"BarTypeTraits":-1,"OpenTraits":0.97755331088664421,"CloseTraits":-1,"Atr":16.010000000000002},"OrderFlowData":{"DeltaPercentage":-21.850000000000001,"ImbalanceMetric":-3.9999999999}}},{"TradeDirection":1,"TradeOutcome":0,"PreTradeBars":[{"DataBar":{"BarTypeTraits":-1,"OpenTraits":0.76623376623376627,"CloseTraits":-0.55844155844155841,"Atr":20.02},"DeltaBar":{"BarTypeTraits":-1,"OpenTraits":0.8990825688073395,"CloseTraits":-0.87155963302752293,"Atr":20.02},"OrderFlowData":{"DeltaPercentage":-16.899999999999999,"ImbalanceMetric":-1.9999999999}},{"DataBar":{"BarTypeTraits":1,"OpenTraits":-0.92592592592592593,"CloseTraits":0.53086419753086422,"Atr":19.719999999999999},"DeltaBar":{"BarTypeTraits":1,"OpenTraits":-0.86725663716814161,"CloseTraits":0.37168141592920356,"Atr":19.719999999999999},"OrderFlowData":{"DeltaPercentage":10.82,"ImbalanceMetric":2.9999999999}},{"DataBar":{"BarTypeTraits":1,"OpenTraits":-0.68421052631578949,"CloseTraits":0.33333333333333331,"Atr":18.859999999999999},"DeltaBar":{"BarTypeTraits":1,"OpenTraits":-0.77777777777777779,"CloseTraits":0.43703703703703706,"Atr":18.859999999999999},"OrderFlowData":{"DeltaPercentage":12.140000000000001,"ImbalanceMetric":0.99999999996666666}}],"CurrentBar":{"DataBar":{"BarTypeTraits":1,"OpenTraits":-0.65517241379310343,"CloseTraits":1,"Atr":19.75},"DeltaBar":{"BarTypeTraits":1,"OpenTraits":-0.78294573643410847,"CloseTraits":0.93798449612403101,"Atr":19.75},"OrderFlowData":{"DeltaPercentage":12.18,"ImbalanceMetric":4.9999999999}}},{"TradeDirection":1,"TradeOutcome":0,"PreTradeBars":[{"DataBar":{"BarTypeTraits":-1,"OpenTraits":0.65517241379310343,"CloseTraits":0.31034482758620691,"Atr":19.260000000000002},"DeltaBar":{"BarTypeTraits":-1,"OpenTraits":0.90756302521008403,"CloseTraits":0.41176470588235292,"Atr":19.260000000000002},"OrderFlowData":{"DeltaPercentage":-4.3799999999999999,"ImbalanceMetric":-1.99999999995}},{"DataBar":{"BarTypeTraits":1,"OpenTraits":-0.27868852459016391,"CloseTraits":0.63934426229508201,"Atr":20.23},"DeltaBar":{"BarTypeTraits":1,"OpenTraits":-0.79411764705882348,"CloseTraits":0.7720588235294118,"Atr":20.23},"OrderFlowData":{"DeltaPercentage":20.530000000000001,"ImbalanceMetric":0}},{"DataBar":{"BarTypeTraits":1,"OpenTraits":-0.086956521739130432,"CloseTraits":0.086956521739130432,"Atr":19.609999999999999},"DeltaBar":{"BarTypeTraits":1,"OpenTraits":-1,"CloseTraits":0.13089005235602094,"Atr":19.609999999999999},"OrderFlowData":{"DeltaPercentage":7.1900000000000004,"ImbalanceMetric":0.99999999989999999}}],"CurrentBar":{"DataBar":{"BarTypeTraits":1,"OpenTraits":-0.83606557377049184,"CloseTraits":1,"Atr":18.460000000000001},"DeltaBar":{"BarTypeTraits":1,"OpenTraits":-0.946257197696737,"CloseTraits":0.90019193857965452,"Atr":18.460000000000001},"OrderFlowData":{"DeltaPercentage":26.399999999999999,"ImbalanceMetric":3.9999999999333333}}},{"TradeDirection":1,"TradeOutcome":1,"PreTradeBars":[{"DataBar":{"BarTypeTraits":-1,"OpenTraits":0.75,"CloseTraits":-0.17857142857142858,"Atr":15.31},"DeltaBar":{"BarTypeTraits":-1,"OpenTraits":0.87027027027027026,"CloseTraits":-0.23243243243243245,"Atr":15.31},"OrderFlowData":{"DeltaPercentage":-9.2599999999999998,"ImbalanceMetric":-0.99999999989999999}},{"DataBar":{"BarTypeTraits":1,"OpenTraits":-0.98165137614678899,"CloseTraits":0.6330275229357798,"Atr":16.16},"DeltaBar":{"BarTypeTraits":1,"OpenTraits":-1,"CloseTraits":0.375,"Atr":16.16},"OrderFlowData":{"DeltaPercentage":16.890000000000001,"ImbalanceMetric":1.99999999995}},{"DataBar":{"BarTypeTraits":1,"OpenTraits":-0.96875,"CloseTraits":0.453125,"Atr":18.539999999999999},"DeltaBar":{"BarTypeTraits":1,"OpenTraits":-0.92361111111111116,"CloseTraits":0.45833333333333331,"Atr":18.539999999999999},"OrderFlowData":{"DeltaPercentage":7.46,"ImbalanceMetric":3.9999999999333333}}],"CurrentBar":{"DataBar":{"BarTypeTraits":1,"OpenTraits":-0.47619047619047616,"CloseTraits":1,"Atr":18.710000000000001},"DeltaBar":{"BarTypeTraits":1,"OpenTraits":0.056603773584905662,"CloseTraits":1,"Atr":18.710000000000001},"OrderFlowData":{"DeltaPercentage":8.0899999999999999,"ImbalanceMetric":1.9999999999}}},{"TradeDirection":1,"TradeOutcome":1,"PreTradeBars":[{"DataBar":{"BarTypeTraits":1,"OpenTraits":-0.82417582417582413,"CloseTraits":0.89010989010989006,"Atr":18.579999999999998},"DeltaBar":{"BarTypeTraits":1,"OpenTraits":-0.83138173302107732,"CloseTraits":0.98594847775175642,"Atr":18.579999999999998},"OrderFlowData":{"DeltaPercentage":19.940000000000001,"ImbalanceMetric":3.9999999999333333}},{"DataBar":{"BarTypeTraits":-1,"OpenTraits":0.5757575757575758,"CloseTraits":0.090909090909090912,"Atr":18.640000000000001},"DeltaBar":{"BarTypeTraits":-1,"OpenTraits":0.78231292517006801,"CloseTraits":-0.70068027210884354,"Atr":18.640000000000001},"OrderFlowData":{"DeltaPercentage":-10.58,"ImbalanceMetric":0}},{"DataBar":{"BarTypeTraits":1,"OpenTraits":-0.88235294117647056,"CloseTraits":-0.56862745098039214,"Atr":18.57},"DeltaBar":{"BarTypeTraits":1,"OpenTraits":-1,"CloseTraits":-0.15614617940199335,"Atr":18.57},"OrderFlowData":{"DeltaPercentage":8.3699999999999992,"ImbalanceMetric":0}}],"CurrentBar":{"DataBar":{"BarTypeTraits":1,"OpenTraits":-0.82222222222222219,"CloseTraits":1,"Atr":18.57},"DeltaBar":{"BarTypeTraits":1,"OpenTraits":-0.90740740740740744,"CloseTraits":0.87962962962962965,"Atr":18.57},"OrderFlowData":{"DeltaPercentage":10.85,"ImbalanceMetric":2.9999999999}}},{"TradeDirection":1,"TradeOutcome":1,"PreTradeBars":[{"DataBar":{"BarTypeTraits":1,"OpenTraits":-0.84210526315789469,"CloseTraits":-0.21052631578947367,"Atr":17.620000000000001},"DeltaBar":{"BarTypeTraits":1,"OpenTraits":-0.95348837209302328,"CloseTraits":0.73255813953488369,"Atr":17.620000000000001},"OrderFlowData":{"DeltaPercentage":16.789999999999999,"ImbalanceMetric":0.99999999996666666}},{"DataBar":{"BarTypeTraits":1,"OpenTraits":-0.13333333333333333,"CloseTraits":0.26666666666666666,"Atr":16.469999999999999},"DeltaBar":{"BarTypeTraits":1,"OpenTraits":-0.51851851851851849,"CloseTraits":-0.88888888888888884,"Atr":16.469999999999999},"OrderFlowData":{"DeltaPercentage":-1.8799999999999999,"ImbalanceMetric":-1.9999999999}},{"DataBar":{"BarTypeTraits":1,"OpenTraits":-0.59322033898305082,"CloseTraits":0.76271186440677963,"Atr":17.440000000000001},"DeltaBar":{"BarTypeTraits":1,"OpenTraits":-0.78260869565217395,"CloseTraits":0.29565217391304349,"Atr":17.440000000000001},"OrderFlowData":{"DeltaPercentage":9.0800000000000001,"ImbalanceMetric":2.9999999999}}],"CurrentBar":{"DataBar":{"BarTypeTraits":1,"OpenTraits":-1,"CloseTraits":1,"Atr":18.109999999999999},"DeltaBar":{"BarTypeTraits":1,"OpenTraits":-0.81690140845070425,"CloseTraits":0.90140845070422537,"Atr":18.109999999999999},"OrderFlowData":{"DeltaPercentage":12.76,"ImbalanceMetric":1.9999999999}}},{"TradeDirection":1,"TradeOutcome":0,"PreTradeBars":[{"DataBar":{"BarTypeTraits":-1,"OpenTraits":0.76190476190476186,"CloseTraits":-0.42857142857142855,"Atr":19.52},"DeltaBar":{"BarTypeTraits":-1,"OpenTraits":0.75247524752475248,"CloseTraits":-0.43564356435643564,"Atr":19.52},"OrderFlowData":{"DeltaPercentage":-11.539999999999999,"ImbalanceMetric":0}},{"DataBar":{"BarTypeTraits":1,"OpenTraits":0,"CloseTraits":0.13953488372093023,"Atr":20.960000000000001},"DeltaBar":{"BarTypeTraits":1,"OpenTraits":-0.20999999999999999,"CloseTraits":0.31,"Atr":20.960000000000001},"OrderFlowData":{"DeltaPercentage":4.2800000000000002,"ImbalanceMetric":0.99999999989999999}},{"DataBar":{"BarTypeTraits":1,"OpenTraits":-0.67164179104477617,"CloseTraits":0.76119402985074625,"Atr":19.829999999999998},"DeltaBar":{"BarTypeTraits":1,"OpenTraits":-0.41414141414141414,"CloseTraits":0.95959595959595956,"Atr":19.829999999999998},"OrderFlowData":{"DeltaPercentage":7.6600000000000001,"ImbalanceMetric":0}}],"CurrentBar":{"DataBar":{"BarTypeTraits":1,"OpenTraits":-0.22448979591836735,"CloseTraits":1,"Atr":20.050000000000001},"DeltaBar":{"BarTypeTraits":1,"OpenTraits":-1,"CloseTraits":0.82608695652173914,"Atr":20.050000000000001},"OrderFlowData":{"DeltaPercentage":20.390000000000001,"ImbalanceMetric":2.9999999999}}},{"TradeDirection":1,"TradeOutcome":1,"PreTradeBars":[{"DataBar":{"BarTypeTraits":1,"OpenTraits":0.65517241379310343,"CloseTraits":0.72413793103448276,"Atr":15.869999999999999},"DeltaBar":{"BarTypeTraits":1,"OpenTraits":0.52727272727272723,"CloseTraits":-0.12727272727272726,"Atr":15.869999999999999},"OrderFlowData":{"DeltaPercentage":-6.5700000000000003,"ImbalanceMetric":0}},{"DataBar":{"BarTypeTraits":-1,"OpenTraits":0.55555555555555558,"CloseTraits":-0.55555555555555558,"Atr":15.869999999999999},"DeltaBar":{"BarTypeTraits":-1,"OpenTraits":-0.625,"CloseTraits":0.5,"Atr":15.869999999999999},"OrderFlowData":{"DeltaPercentage":7.6600000000000001,"ImbalanceMetric":0.99999999996666666}},{"DataBar":{"BarTypeTraits":1,"OpenTraits":-1,"CloseTraits":0.15789473684210525,"Atr":16.149999999999999},"DeltaBar":{"BarTypeTraits":1,"OpenTraits":-0.97385620915032678,"CloseTraits":0.72549019607843135,"Atr":16.149999999999999},"OrderFlowData":{"DeltaPercentage":24.100000000000001,"ImbalanceMetric":1.9999999999}}],"CurrentBar":{"DataBar":{"BarTypeTraits":1,"OpenTraits":-0.91666666666666663,"CloseTraits":1,"Atr":14.92},"DeltaBar":{"BarTypeTraits":1,"OpenTraits":-1,"CloseTraits":1,"Atr":14.92},"OrderFlowData":{"DeltaPercentage":28.609999999999999,"ImbalanceMetric":1.9999999999}}},{"TradeDirection":1,"TradeOutcome":0,"PreTradeBars":[{"DataBar":{"BarTypeTraits":1,"OpenTraits":-0.75609756097560976,"CloseTraits":0.90243902439024393,"Atr":16.079999999999998},"DeltaBar":{"BarTypeTraits":1,"OpenTraits":-0.80519480519480524,"CloseTraits":0.92207792207792205,"Atr":16.079999999999998},"OrderFlowData":{"DeltaPercentage":23.559999999999999,"ImbalanceMetric":0}},{"DataBar":{"BarTypeTraits":1,"OpenTraits":0.33333333333333331,"CloseTraits":0.81818181818181823,"Atr":14.800000000000001},"DeltaBar":{"BarTypeTraits":1,"OpenTraits":0.7142857142857143,"CloseTraits":0.41496598639455784,"Atr":14.800000000000001},"OrderFlowData":{"DeltaPercentage":-2.8599999999999999,"ImbalanceMetric":0.99999999996666666}},{"DataBar":{"BarTypeTraits":1,"OpenTraits":-0.66666666666666663,"CloseTraits":0.40000000000000002,"Atr":15.300000000000001},"DeltaBar":{"BarTypeTraits":1,"OpenTraits":-0.63235294117647056,"CloseTraits":0.4264705882352941,"Atr":15.300000000000001},"OrderFlowData":{"DeltaPercentage":11.76,"ImbalanceMetric":-0.99999999996666666}}],"CurrentBar":{"DataBar":{"BarTypeTraits":1,"OpenTraits":-0.91666666666666663,"CloseTraits":1,"Atr":16.300000000000001},"DeltaBar":{"BarTypeTraits":1,"OpenTraits":-0.75324675324675328,"CloseTraits":0.87012987012987009,"Atr":16.300000000000001},"OrderFlowData":{"DeltaPercentage":18.82,"ImbalanceMetric":2.9999999999}}},{"TradeDirection":1,"TradeOutcome":1,"PreTradeBars":[{"DataBar":{"BarTypeTraits":1,"OpenTraits":-0.21739130434782608,"CloseTraits":-0.043478260869565216,"Atr":15.140000000000001},"DeltaBar":{"BarTypeTraits":1,"OpenTraits":-1,"CloseTraits":0.54098360655737709,"Atr":15.140000000000001},"OrderFlowData":{"DeltaPercentage":11.640000000000001,"ImbalanceMetric":0}},{"DataBar":{"BarTypeTraits":1,"OpenTraits":-0.33333333333333331,"CloseTraits":0.20000000000000001,"Atr":13.869999999999999},"DeltaBar":{"BarTypeTraits":1,"OpenTraits":-0.64912280701754388,"CloseTraits":0.64912280701754388,"Atr":13.869999999999999},"OrderFlowData":{"DeltaPercentage":8.1300000000000008,"ImbalanceMetric":0}},{"DataBar":{"BarTypeTraits":1,"OpenTraits":-0.40000000000000002,"CloseTraits":-0.33333333333333331,"Atr":14.289999999999999},"DeltaBar":{"BarTypeTraits":1,"OpenTraits":-0.7009345794392523,"CloseTraits":-0.32710280373831774,"Atr":14.289999999999999},"OrderFlowData":{"DeltaPercentage":2.1699999999999999,"ImbalanceMetric":0.99999999996666666}}],"CurrentBar":{"DataBar":{"BarTypeTraits":1,"OpenTraits":-1,"CloseTraits":1,"Atr":14.619999999999999},"DeltaBar":{"BarTypeTraits":1,"OpenTraits":-0.84507042253521125,"CloseTraits":0.92957746478873238,"Atr":14.619999999999999},"OrderFlowData":{"DeltaPercentage":18.710000000000001,"ImbalanceMetric":0.99999999989999999}}},{"TradeDirection":1,"TradeOutcome":1,"PreTradeBars":[{"DataBar":{"BarTypeTraits":0,"OpenTraits":0.33333333333333331,"CloseTraits":0.33333333333333331,"Atr":14.4},"DeltaBar":{"BarTypeTraits":0,"OpenTraits":0.69811320754716977,"CloseTraits":-0.69811320754716977,"Atr":14.4},"OrderFlowData":{"DeltaPercentage":-7.3899999999999997,"ImbalanceMetric":-1.9999999999}},{"DataBar":{"BarTypeTraits":1,"OpenTraits":-1,"CloseTraits":-0.22222222222222221,"Atr":13.84},"DeltaBar":{"BarTypeTraits":1,"OpenTraits":-0.90322580645161288,"CloseTraits":-0.61290322580645162,"Atr":13.84},"OrderFlowData":{"DeltaPercentage":1.9199999999999999,"ImbalanceMetric":0}},{"DataBar":{"BarTypeTraits":1,"OpenTraits":-0.6875,"CloseTraits":0.6875,"Atr":14.039999999999999},"DeltaBar":{"BarTypeTraits":1,"OpenTraits":-0.31578947368421051,"CloseTraits":-0.71052631578947367,"Atr":14.039999999999999},"OrderFlowData":{"DeltaPercentage":-3.3399999999999999,"ImbalanceMetric":1.9999999999}}],"CurrentBar":{"DataBar":{"BarTypeTraits":1,"OpenTraits":-0.95652173913043481,"CloseTraits":1,"Atr":13.65},"DeltaBar":{"BarTypeTraits":1,"OpenTraits":-1,"CloseTraits":0.79723502304147464,"Atr":13.65},"OrderFlowData":{"DeltaPercentage":17.98,"ImbalanceMetric":4.9999999999}}},{"TradeDirection":1,"TradeOutcome":1,"PreTradeBars":[{"DataBar":{"BarTypeTraits":1,"OpenTraits":-0.6875,"CloseTraits":0.6875,"Atr":14.039999999999999},"DeltaBar":{"BarTypeTraits":1,"OpenTraits":-0.31578947368421051,"CloseTraits":-0.71052631578947367,"Atr":14.039999999999999},"OrderFlowData":{"DeltaPercentage":-3.3399999999999999,"ImbalanceMetric":1.9999999999}},{"DataBar":{"BarTypeTraits":1,"OpenTraits":-0.97674418604651159,"CloseTraits":0.81395348837209303,"Atr":14.85},"DeltaBar":{"BarTypeTraits":1,"OpenTraits":-1,"CloseTraits":0.9887640449438202,"Atr":14.85},"OrderFlowData":{"DeltaPercentage":17.98,"ImbalanceMetric":7.9999999999}},{"DataBar":{"BarTypeTraits":1,"OpenTraits":-0.70731707317073167,"CloseTraits":0.80487804878048785,"Atr":14.43},"DeltaBar":{"BarTypeTraits":1,"OpenTraits":-0.98484848484848486,"CloseTraits":0.98484848484848486,"Atr":14.43},"OrderFlowData":{"DeltaPercentage":14.67,"ImbalanceMetric":1.99999999995}}],"CurrentBar":{"DataBar":{"BarTypeTraits":1,"OpenTraits":-1,"CloseTraits":1,"Atr":15.289999999999999},"DeltaBar":{"BarTypeTraits":1,"OpenTraits":-1,"CloseTraits":0.49056603773584906,"Atr":15.289999999999999},"OrderFlowData":{"DeltaPercentage":11.17,"ImbalanceMetric":2.9999999999}}},{"TradeDirection":1,"TradeOutcome":0,"PreTradeBars":[{"DataBar":{"BarTypeTraits":0,"OpenTraits":-0.1111111111111111,"CloseTraits":-0.1111111111111111,"Atr":14.75},"DeltaBar":{"BarTypeTraits":0,"OpenTraits":0.23353293413173654,"CloseTraits":-0.58083832335329344,"Atr":14.75},"OrderFlowData":{"DeltaPercentage":-3.5899999999999999,"ImbalanceMetric":-1.9999999999666667}},{"DataBar":{"BarTypeTraits":-1,"OpenTraits":-0.125,"CloseTraits":-0.90000000000000002,"Atr":16.030000000000001},"DeltaBar":{"BarTypeTraits":-1,"OpenTraits":0.30341113105924594,"CloseTraits":-0.99281867145421898,"Atr":16.030000000000001},"OrderFlowData":{"DeltaPercentage":-11.710000000000001,"ImbalanceMetric":-3.99999999995}},{"DataBar":{"BarTypeTraits":1,"OpenTraits":-0.16326530612244897,"CloseTraits":0.97959183673469385,"Atr":17.559999999999999},"DeltaBar":{"BarTypeTraits":1,"OpenTraits":0.85858585858585856,"CloseTraits":0.27946127946127947,"Atr":17.559999999999999},"OrderFlowData":{"DeltaPercentage":-3.73,"ImbalanceMetric":-1.9999999999666667}}],"CurrentBar":{"DataBar":{"BarTypeTraits":1,"OpenTraits":-0.076923076923076927,"CloseTraits":1,"Atr":16.329999999999998},"DeltaBar":{"BarTypeTraits":1,"OpenTraits":-0.98198198198198194,"CloseTraits":0.81981981981981977,"Atr":16.329999999999998},"OrderFlowData":{"DeltaPercentage":10.08,"ImbalanceMetric":1.9999999999}}}]